funcaptcha_challenger/BrokenJigsawbrokenjigsaw_swap.py
funcaptcha_challenger/__init__.py
funcaptcha_challenger/card.py
funcaptcha_challenger/cardistance.py
funcaptcha_challenger/conveyor.py
funcaptcha_challenger/coordinatesmatch.py
funcaptcha_challenger/counting.py
funcaptcha_challenger/dicematch.py
funcaptcha_challenger/frankenhead.py
funcaptcha_challenger/hand_number_puzzle.py
funcaptcha_challenger/hopscotch_highsec.py
funcaptcha_challenger/knotsCrossesCircle.py
funcaptcha_challenger/model.py
funcaptcha_challenger/penguins.py
funcaptcha_challenger/penguins_icon.py
funcaptcha_challenger/predictor.py
funcaptcha_challenger/rockstack.py
funcaptcha_challenger/shadows.py
funcaptcha_challenger/threed_rollball_animal.py
funcaptcha_challenger/threed_rollball_objects.py
funcaptcha_challenger/tools.py
funcaptcha_challenger/train_coordinates.py
funcaptcha_challenger/unbentobjects.py
funcaptcha_challenger-0.17.7.dist-info/METADATA
funcaptcha_challenger-0.17.7.dist-info/WHEEL
funcaptcha_challenger-0.17.7.dist-info/RECORD
